claif/__init__.py
claif/__version__.py
claif/cli.py
claif/client.py
claif-1.0.33.dist-info/METADATA
claif-1.0.33.dist-info/WHEEL
claif-1.0.33.dist-info/entry_points.txt
claif-1.0.33.dist-info/licenses/LICENSE
claif-1.0.33.dist-info/RECORD
