Metadata-Version: 2.4
Name: claif
Version: 1.0.33
Summary: A unified CLI and Python library for interacting with local and remote LLMs, compatible with the OpenAI Responses API.
Project-URL: Documentation, https://github.com/twardoch/claif#readme
Project-URL: Issues, https://github.com/twardoch/claif/issues
Project-URL: Source, https://github.com/twardoch/claif
Author-email: Adam Twardoch <adam+github@twardoch.com>
License: MIT
License-File: LICENSE
Keywords: ai,artificial-intelligence,claif,claude,cli,codex,command-line,gemini,llm,lm-studio,openai,responses-api
Classifier: Development Status :: 4 - Beta
Classifier: Intended Audience :: Developers
Classifier: License :: OSI Approved :: MIT License
Classifier: Operating System :: OS Independent
Classifier: Programming Language :: Python
Classifier: Programming Language :: Python :: 3.10
Classifier: Programming Language :: Python :: 3.11
Classifier: Programming Language :: Python :: 3.12
Classifier: Programming Language :: Python :: Implementation :: CPython
Classifier: Programming Language :: Python :: Implementation :: PyPy
Requires-Python: >=3.10
Requires-Dist: fastmcp>=2.9.2
Requires-Dist: fire>=0.7.0
Requires-Dist: importlib-metadata>=8.7.0
Requires-Dist: importlib-resources>=6.5.2
Requires-Dist: loguru>=0.7.0
Requires-Dist: openai>=1.0.0
Requires-Dist: platformdirs>=4.0.0
Requires-Dist: pydantic>=2.0.0
Requires-Dist: rich>=13.9.4
Requires-Dist: tenacity>=9.0.0
Requires-Dist: typing-extensions>=4.0.0; python_version < '3.11'
Requires-Dist: uvicorn>=0.34.1
Provides-Extra: all
Requires-Dist: claif-cla>=1.0.0; extra == 'all'
Requires-Dist: claif-cod>=1.0.0; extra == 'all'
Requires-Dist: claif-gem>=1.0.0; extra == 'all'
Requires-Dist: claif-lms>=0.0.1; extra == 'all'
Requires-Dist: fastmcp>=2.9.2; extra == 'all'
Requires-Dist: fire>=0.7.0; extra == 'all'
Requires-Dist: importlib-metadata>=8.7.0; extra == 'all'
Requires-Dist: importlib-resources>=6.5.2; extra == 'all'
Requires-Dist: loguru>=0.7.0; extra == 'all'
Requires-Dist: openai>=1.0.0; extra == 'all'
Requires-Dist: platformdirs>=4.0.0; extra == 'all'
Requires-Dist: pydantic>=2.0.0; extra == 'all'
Requires-Dist: rich>=13.9.4; extra == 'all'
Requires-Dist: tenacity>=9.0.0; extra == 'all'
Requires-Dist: typing-extensions>=4.0.0; (python_version < '3.11') and extra == 'all'
Requires-Dist: uvicorn>=0.34.1; extra == 'all'
Provides-Extra: dev
Requires-Dist: absolufy-imports>=0.3.1; extra == 'dev'
Requires-Dist: isort>=6.0.1; extra == 'dev'
Requires-Dist: mypy>=1.15.0; extra == 'dev'
Requires-Dist: pre-commit>=4.1.0; extra == 'dev'
Requires-Dist: pyupgrade>=3.19.1; extra == 'dev'
Requires-Dist: ruff>=0.9.7; extra == 'dev'
Provides-Extra: docs
Requires-Dist: myst-parser>=4.0.1; extra == 'docs'
Requires-Dist: sphinx-autodoc-typehints>=3.2.0; extra == 'docs'
Requires-Dist: sphinx-rtd-theme>=3.0.2; extra == 'docs'
Requires-Dist: sphinx>=8.2.3; extra == 'docs'
Provides-Extra: providers
Requires-Dist: claif-cla>=1.0.0; extra == 'providers'
Requires-Dist: claif-cod>=1.0.0; extra == 'providers'
Requires-Dist: claif-gem>=1.0.0; extra == 'providers'
Requires-Dist: claif-lms>=0.0.1; extra == 'providers'
Provides-Extra: test
Requires-Dist: coverage[toml]>=7.6.12; extra == 'test'
Requires-Dist: pytest-asyncio>=0.26.0; extra == 'test'
Requires-Dist: pytest-benchmark[histogram]>=5.1.0; extra == 'test'
Requires-Dist: pytest-cov>=6.0.0; extra == 'test'
Requires-Dist: pytest-xdist>=3.6.1; extra == 'test'
Requires-Dist: pytest>=8.3.4; extra == 'test'
